{"children":[{"id":"1752660650965","campId":"PC2025-001-ΝΠ","firstName":"Νικος","lastName":"Παπαδοπουλος","age":13,"group":"Μπλε","balance":96,"dailyLimit":5,"allowOverride":true,"todaySpent":6,"lastSpendingReset":"2025-07-16","notes":"","createdAt":"2025-07-16T10:10:50.965Z"},{"id":"1752661540157","campId":"PC2025-002-ΠΦ","firstName":"Πέτρος","lastName":"Φιλόπουλος","age":12,"group":"Πράσινη","balance":20,"dailyLimit":5,"allowOverride":true,"todaySpent":0,"lastSpendingReset":"2025-07-16","notes":"","createdAt":"2025-07-16T10:25:40.157Z"},{"id":"1752661650001","campId":"PC2025-003-ΜΚ","firstName":"Μαρία","lastName":"Κωνσταντίνου","age":14,"group":"Κόκκινη","balance":75,"dailyLimit":8,"allowOverride":true,"todaySpent":2,"lastSpendingReset":"2025-07-16","notes":"Υπεύθυνη ομάδας","createdAt":"2025-07-16T09:00:00.000Z"},{"id":"1752661650002","campId":"PC2025-004-ΑΒ","firstName":"Αλέξανδρος","lastName":"Βασιλείου","age":15,"group":"Κίτρινη","balance":150,"dailyLimit":10,"allowOverride":true,"todaySpent":5,"lastSpendingReset":"2025-07-16","notes":"","createdAt":"2025-07-16T09:15:00.000Z"},{"id":"1752661650003","campId":"PC2025-005-ΣΜ","firstName":"Σοφία","lastName":"Μιχαηλίδου","age":11,"group":"Μπλε","balance":45,"dailyLimit":4,"allowOverride":true,"todaySpent":0,"lastSpendingReset":"2025-07-16","notes":"","createdAt":"2025-07-16T09:30:00.000Z"},{"id":"1752661650004","campId":"PC2025-006-ΓΣ","firstName":"Γιάννης","lastName":"Σταματόπουλος","age":10,"group":"Πράσινη","balance":30,"dailyLimit":3,"allowOverride":false,"todaySpent":3,"lastSpendingReset":"2025-07-16","notes":"Δεν επιτρέπεται παράκαμψη","createdAt":"2025-07-16T09:45:00.000Z"},{"id":"1752661650005","campId":"PC2025-007-ΕΘ","firstName":"Ελένη","lastName":"Θεοδώρου","age":16,"group":"Κόκκινη","balance":200,"dailyLimit":15,"allowOverride":true,"todaySpent":8,"lastSpendingReset":"2025-07-16","notes":"Μεγάλη ηλικία","createdAt":"2025-07-16T08:00:00.000Z"},{"id":"1752661650006","campId":"PC2025-008-ΔΑ","firstName":"Δημήτρης","lastName":"Αντωνίου","age":9,"group":"Κίτρινη","balance":15,"dailyLimit":2,"allowOverride":true,"todaySpent":1,"lastSpendingReset":"2025-07-16","notes":"","createdAt":"2025-07-16T08:15:00.000Z"},{"id":"1752661650007","campId":"PC2025-009-ΚΠ","firstName":"Κατερίνα","lastName":"Παναγιώτου","age":12,"group":"Μπλε","balance":65,"dailyLimit":6,"allowOverride":true,"todaySpent":4,"lastSpendingReset":"2025-07-16","notes":"","createdAt":"2025-07-16T08:30:00.000Z"},{"id":"1752661650008","campId":"PC2025-010-ΑΓ","firstName":"Αντώνης","lastName":"Γεωργίου","age":13,"group":"Πράσινη","balance":85,"dailyLimit":7,"allowOverride":true,"todaySpent":2,"lastSpendingReset":"2025-07-16","notes":"","createdAt":"2025-07-16T08:45:00.000Z"},{"id":"1752661650009","campId":"PC2025-011-ΧΛ","firstName":"Χριστίνα","lastName":"Λάμπρου","age":14,"group":"Κόκκινη","balance":110,"dailyLimit":9,"allowOverride":true,"todaySpent":6,"lastSpendingReset":"2025-07-16","notes":"","createdAt":"2025-07-16T07:00:00.000Z"},{"id":"1752661650010","campId":"PC2025-012-ΙΚ","firstName":"Ιωάννης","lastName":"Καραμανλής","age":8,"group":"Κίτρινη","balance":25,"dailyLimit":2.5,"allowOverride":true,"todaySpent":0,"lastSpendingReset":"2025-07-16","notes":"Μικρή ηλικία","createdAt":"2025-07-16T07:15:00.000Z"},{"id":"1752661650011","campId":"PC2025-013-ΦΡ","firstName":"Φωτεινή","lastName":"Ρούσσου","age":15,"group":"Μπλε","balance":120,"dailyLimit":12,"allowOverride":true,"todaySpent":10,"lastSpendingReset":"2025-07-16","notes":"","createdAt":"2025-07-16T07:30:00.000Z"},{"id":"1752661650012","campId":"PC2025-014-ΝΔ","firstName":"Νίκος","lastName":"Δημητρίου","age":11,"group":"Πράσινη","balance":55,"dailyLimit":5,"allowOverride":true,"todaySpent":3,"lastSpendingReset":"2025-07-16","notes":"","createdAt":"2025-07-16T07:45:00.000Z"},{"id":"1752661650013","campId":"PC2025-015-ΒΜ","firstName":"Βασιλική","lastName":"Μαρίνου","age":17,"group":"Κόκκινη","balance":182,"dailyLimit":0,"allowOverride":true,"todaySpent":0,"lastSpendingReset":"2025-07-16","notes":"Απεριόριστο όριο","createdAt":"2025-07-16T06:00:00.000Z"},{"id":"1752661650014","campId":"PC2025-016-ΤΠ","firstName":"Θάνος","lastName":"Παπαγιάννης","age":10,"group":"Κίτρινη","balance":40,"dailyLimit":4,"allowOverride":true,"todaySpent":2,"lastSpendingReset":"2025-07-16","notes":"","createdAt":"2025-07-16T06:15:00.000Z"},{"id":"1752661650015","campId":"PC2025-017-ΛΤ","firstName":"Λίλα","lastName":"Τσάκου","age":13,"group":"Μπλε","balance":70,"dailyLimit":6,"allowOverride":false,"todaySpent":5,"lastSpendingReset":"2025-07-16","notes":"Δεν επιτρέπεται παράκαμψη","createdAt":"2025-07-16T06:30:00.000Z"},{"id":"1752661650016","campId":"PC2025-018-ΜΧ","firstName":"Μανώλης","lastName":"Χατζής","age":16,"group":"Πράσινη","balance":95,"dailyLimit":10,"allowOverride":true,"todaySpent":8,"lastSpendingReset":"2025-07-16","notes":"","createdAt":"2025-07-16T06:45:00.000Z"},{"id":"1752661650017","campId":"PC2025-019-ΕΞ","firstName":"Ευαγγελία","lastName":"Ξένου","age":12,"group":"Κόκκινη","balance":35,"dailyLimit":4,"allowOverride":true,"todaySpent":1,"lastSpendingReset":"2025-07-16","notes":"","createdAt":"2025-07-16T05:00:00.000Z"},{"id":"1752661650018","campId":"PC2025-020-ΡΩ","firstName":"Ρένα","lastName":"Ωμέγα","age":14,"group":"Κίτρινη","balance":90,"dailyLimit":8,"allowOverride":true,"todaySpent":4,"lastSpendingReset":"2025-07-16","notes":"","createdAt":"2025-07-16T05:15:00.000Z"}],"transactions":[{"id":"1752660650966","childId":"1752660650965","type":"deposit","amount":100,"date":"2025-07-16T10:10:50.966Z","staff":"Διαχειριστής","notes":"Αρχικό υπόλοιπο"},{"id":"1752661034473","childId":"1752660650965","type":"withdraw","amount":2,"date":"2025-07-16T10:17:14.473Z","staff":"Διαχειριστής","notes":"","oldBalance":100,"newBalance":98,"limitOverride":false},{"id":"1752661394446","childId":"1752660650965","type":"withdraw","amount":3,"date":"2025-07-16T10:23:14.446Z","staff":"Διαχειριστής","notes":"","oldBalance":98,"newBalance":95,"limitOverride":false},{"id":"1752661413249","childId":"1752660650965","type":"withdraw","amount":1,"date":"2025-07-16T10:23:33.249Z","staff":"Διαχειριστής","notes":"[ΠΑΡΑΚΑΜΨΗ ΟΡΙΟΥ] tesg esfes f sedfse\n[ΠΑΡΑΚΑΜΨΗ ΟΡΙΟΥ] sfefsfegsefg","oldBalance":95,"newBalance":94,"limitOverride":true},{"id":"1752661540157","childId":"1752661540157","type":"deposit","amount":20,"date":"2025-07-16T10:25:40.157Z","staff":"Διαχειριστής","notes":"Αρχικό υπόλοιπο"},{"id":"1752661553173","childId":"1752660650965","type":"deposit","amount":2,"date":"2025-07-16T10:25:53.173Z","staff":"Διαχειριστής","notes":"","oldBalance":94,"newBalance":96,"limitOverride":false},{"id":"1752661650101","childId":"1752661650003","type":"deposit","amount":50,"date":"2025-07-16T09:30:00.100Z","staff":"Προσωπικό 1","notes":"Αρχικό υπόλοιπο"},{"id":"1752661650102","childId":"1752661650004","type":"deposit","amount":35,"date":"2025-07-16T09:45:00.100Z","staff":"Προσωπικό 1","notes":"Αρχικό υπόλοιπο"},{"id":"1752661650103","childId":"1752661650005","type":"deposit","amount":220,"date":"2025-07-16T08:00:00.100Z","staff":"Διαχειριστής","notes":"Αρχικό υπόλοιπο"},{"id":"1752661650104","childId":"1752661650006","type":"deposit","amount":18,"date":"2025-07-16T08:15:00.100Z","staff":"Προσωπικό 1","notes":"Αρχικό υπόλοιπο"},{"id":"1752661650105","childId":"1752661650007","type":"deposit","amount":75,"date":"2025-07-16T08:30:00.100Z","staff":"Διαχειριστής","notes":"Αρχικό υπόλοιπο"},{"id":"1752661650106","childId":"1752661650008","type":"deposit","amount":90,"date":"2025-07-16T08:45:00.100Z","staff":"Προσωπικό 1","notes":"Αρχικό υπόλοιπο"},{"id":"1752661650107","childId":"1752661650009","type":"deposit","amount":125,"date":"2025-07-16T07:00:00.100Z","staff":"Διαχειριστής","notes":"Αρχικό υπόλοιπο"},{"id":"1752661650108","childId":"1752661650010","type":"deposit","amount":25,"date":"2025-07-16T07:15:00.100Z","staff":"Προσωπικό 1","notes":"Αρχικό υπόλοιπο"},{"id":"1752661650109","childId":"1752661650011","type":"deposit","amount":140,"date":"2025-07-16T07:30:00.100Z","staff":"Διαχειριστής","notes":"Αρχικό υπόλοιπο"},{"id":"1752661650110","childId":"1752661650012","type":"deposit","amount":65,"date":"2025-07-16T07:45:00.100Z","staff":"Προσωπικό 1","notes":"Αρχικό υπόλοιπο"},{"id":"1752661650111","childId":"1752661650013","type":"deposit","amount":180,"date":"2025-07-16T06:00:00.100Z","staff":"Διαχειριστής","notes":"Αρχικό υπόλοιπο"},{"id":"1752661650112","childId":"1752661650014","type":"deposit","amount":45,"date":"2025-07-16T06:15:00.100Z","staff":"Προσωπικό 1","notes":"Αρχικό υπόλοιπο"},{"id":"1752661650113","childId":"1752661650015","type":"deposit","amount":80,"date":"2025-07-16T06:30:00.100Z","staff":"Διαχειριστής","notes":"Αρχικό υπόλοιπο"},{"id":"1752661650114","childId":"1752661650016","type":"deposit","amount":110,"date":"2025-07-16T06:45:00.100Z","staff":"Προσωπικό 1","notes":"Αρχικό υπόλοιπο"},{"id":"1752661650115","childId":"1752661650017","type":"deposit","amount":40,"date":"2025-07-16T05:00:00.100Z","staff":"Διαχειριστής","notes":"Αρχικό υπόλοιπο"},{"id":"1752661650116","childId":"1752661650018","type":"deposit","amount":100,"date":"2025-07-16T05:15:00.100Z","staff":"Προσωπικό 1","notes":"Αρχικό υπόλοιπο"},{"id":"1752661650201","childId":"1752661650001","type":"deposit","amount":80,"date":"2025-07-16T09:00:00.200Z","staff":"Διαχειριστής","notes":"Αρχικό υπόλοιπο"},{"id":"1752661650202","childId":"1752661650002","type":"deposit","amount":160,"date":"2025-07-16T09:15:00.200Z","staff":"Προσωπικό 1","notes":"Αρχικό υπόλοιπο"},{"id":"1752661650301","childId":"1752661650003","type":"withdraw","amount":5,"date":"2025-07-16T11:00:00.300Z","staff":"Διαχειριστής","notes":"Κυλικείο","oldBalance":50,"newBalance":45,"limitOverride":false},{"id":"1752661650302","childId":"1752661650004","type":"withdraw","amount":5,"date":"2025-07-16T11:15:00.300Z","staff":"Προσωπικό 1","notes":"Κυλικείο","oldBalance":35,"newBalance":30,"limitOverride":false},{"id":"1752661650303","childId":"1752661650005","type":"withdraw","amount":12,"date":"2025-07-16T11:30:00.300Z","staff":"Διαχειριστής","notes":"Αγορές","oldBalance":220,"newBalance":208,"limitOverride":false},{"id":"1752661650304","childId":"1752661650005","type":"withdraw","amount":8,"date":"2025-07-16T12:00:00.300Z","staff":"Προσωπικό 1","notes":"Επιπλέον αγορές","oldBalance":208,"newBalance":200,"limitOverride":false},{"id":"1752661650305","childId":"1752661650006","type":"withdraw","amount":1,"date":"2025-07-16T11:45:00.300Z","staff":"Διαχειριστής","notes":"Σοκολάτα","oldBalance":18,"newBalance":17,"limitOverride":false},{"id":"1752661650306","childId":"1752661650006","type":"withdraw","amount":2,"date":"2025-07-16T12:15:00.300Z","staff":"Προσωπικό 1","notes":"Χυμός","oldBalance":17,"newBalance":15,"limitOverride":false},{"id":"1752661650307","childId":"1752661650007","type":"withdraw","amount":4,"date":"2025-07-16T12:30:00.300Z","staff":"Διαχειριστής","notes":"Κυλικείο","oldBalance":75,"newBalance":71,"limitOverride":false},{"id":"1752661650308","childId":"1752661650007","type":"withdraw","amount":6,"date":"2025-07-16T13:00:00.300Z","staff":"Προσωπικό 1","notes":"Παγωτό","oldBalance":71,"newBalance":65,"limitOverride":false},{"id":"1752661650309","childId":"1752661650008","type":"withdraw","amount":3,"date":"2025-07-16T12:45:00.300Z","staff":"Διαχειριστής","notes":"Αναψυκτικό","oldBalance":90,"newBalance":87,"limitOverride":false},{"id":"1752661650310","childId":"1752661650008","type":"withdraw","amount":2,"date":"2025-07-16T13:15:00.300Z","staff":"Προσωπικό 1","notes":"Τσίχλες","oldBalance":87,"newBalance":85,"limitOverride":false},{"id":"1752661650311","childId":"1752661650009","type":"withdraw","amount":8,"date":"2025-07-16T13:30:00.300Z","staff":"Διαχειριστής","notes":"Αγορές","oldBalance":125,"newBalance":117,"limitOverride":false},{"id":"1752661650312","childId":"1752661650009","type":"withdraw","amount":7,"date":"2025-07-16T14:00:00.300Z","staff":"Προσωπικό 1","notes":"Επιπλέον","oldBalance":117,"newBalance":110,"limitOverride":false},{"id":"1752661650313","childId":"1752661650011","type":"withdraw","amount":10,"date":"2025-07-16T13:45:00.300Z","staff":"Διαχειριστής","notes":"Κυλικείο","oldBalance":140,"newBalance":130,"limitOverride":false},{"id":"1752661650314","childId":"1752661650011","type":"withdraw","amount":10,"date":"2025-07-16T14:15:00.300Z","staff":"Προσωπικό 1","notes":"Παγωτό","oldBalance":130,"newBalance":120,"limitOverride":false},{"id":"1752661650315","childId":"1752661650012","type":"withdraw","amount":5,"date":"2025-07-16T14:30:00.300Z","staff":"Διαχειριστής","notes":"Κυλικείο","oldBalance":65,"newBalance":60,"limitOverride":false},{"id":"1752661650316","childId":"1752661650012","type":"withdraw","amount":5,"date":"2025-07-16T15:00:00.300Z","staff":"Προσωπικό 1","notes":"Αναψυκτικό","oldBalance":60,"newBalance":55,"limitOverride":false},{"id":"1752661650317","childId":"1752661650014","type":"withdraw","amount":3,"date":"2025-07-16T14:45:00.300Z","staff":"Διαχειριστής","notes":"Κυλικείο","oldBalance":45,"newBalance":42,"limitOverride":false},{"id":"1752661650318","childId":"1752661650014","type":"withdraw","amount":2,"date":"2025-07-16T15:15:00.300Z","staff":"Προσωπικό 1","notes":"Τσιπς","oldBalance":42,"newBalance":40,"limitOverride":false},{"id":"1752661650319","childId":"1752661650015","type":"withdraw","amount":5,"date":"2025-07-16T15:30:00.300Z","staff":"Διαχειριστής","notes":"Κυλικείο","oldBalance":80,"newBalance":75,"limitOverride":false},{"id":"1752661650320","childId":"1752661650015","type":"withdraw","amount":5,"date":"2025-07-16T16:00:00.300Z","staff":"Προσωπικό 1","notes":"Γλυκά","oldBalance":75,"newBalance":70,"limitOverride":false},{"id":"1752661650321","childId":"1752661650016","type":"withdraw","amount":8,"date":"2025-07-16T15:45:00.300Z","staff":"Διαχειριστής","notes":"Κυλικείο","oldBalance":110,"newBalance":102,"limitOverride":false},{"id":"1752661650322","childId":"1752661650016","type":"withdraw","amount":7,"date":"2025-07-16T16:15:00.300Z","staff":"Προσωπικό 1","notes":"Παγωτό","oldBalance":102,"newBalance":95,"limitOverride":false},{"id":"1752661650323","childId":"1752661650017","type":"withdraw","amount":3,"date":"2025-07-16T16:30:00.300Z","staff":"Διαχειριστής","notes":"Κυλικείο","oldBalance":40,"newBalance":37,"limitOverride":false},{"id":"1752661650324","childId":"1752661650017","type":"withdraw","amount":2,"date":"2025-07-16T17:00:00.300Z","staff":"Προσωπικό 1","notes":"Χυμός","oldBalance":37,"newBalance":35,"limitOverride":false},{"id":"1752661650325","childId":"1752661650018","type":"withdraw","amount":6,"date":"2025-07-16T16:45:00.300Z","staff":"Διαχειριστής","notes":"Κυλικείο","oldBalance":100,"newBalance":94,"limitOverride":false},{"id":"1752661650326","childId":"1752661650018","type":"withdraw","amount":4,"date":"2025-07-16T17:15:00.300Z","staff":"Προσωπικό 1","notes":"Αναψυκτικό","oldBalance":94,"newBalance":90,"limitOverride":false},{"id":"1752661650327","childId":"1752661650001","type":"withdraw","amount":2,"date":"2025-07-16T16:00:00.300Z","staff":"Διαχειριστής","notes":"Κυλικείο","oldBalance":80,"newBalance":78,"limitOverride":false},{"id":"1752661650328","childId":"1752661650001","type":"withdraw","amount":3,"date":"2025-07-16T17:30:00.300Z","staff":"Προσωπικό 1","notes":"Παγωτό","oldBalance":78,"newBalance":75,"limitOverride":false},{"id":"1752661650329","childId":"1752661650002","type":"withdraw","amount":5,"date":"2025-07-16T17:00:00.300Z","staff":"Διαχειριστής","notes":"Κυλικείο","oldBalance":160,"newBalance":155,"limitOverride":false},{"id":"1752661650330","childId":"1752661650002","type":"withdraw","amount":5,"date":"2025-07-16T17:45:00.300Z","staff":"Προσωπικό 1","notes":"Γλυκά","oldBalance":155,"newBalance":150,"limitOverride":false},{"id":"1752661650331","childId":"1752661650004","type":"withdraw","amount":3,"date":"2025-07-16T16:30:00.300Z","staff":"Διαχειριστής","notes":"[ΠΑΡΑΚΑΜΨΗ ΟΡΙΟΥ] Έκτακτη ανάγκη","oldBalance":30,"newBalance":27,"limitOverride":true},{"id":"1752665076427","childId":"1752661650013","type":"deposit","amount":2,"date":"2025-07-16T11:24:36.427Z","staff":"Διαχειριστής","notes":"","oldBalance":180,"newBalance":182,"limitOverride":false}],"settings":{"itemsPerPage":10,"defaultDailyLimit":5,"autoBackup":false,"soundNotifications":true,"darkMode":false,"keyboardShortcuts":true,"smartAlerts":false},"timestamp":"2025-07-16T11:31:34.717Z"}